{
  "code": 200,
  "status": 20000,
  "data": {
    "links": {
      "": "https://www.onetrust.com/products/cookie-consent/",
      "AI Presentation Maker Create presentations in minutes with AI": "https://slidesgo.com/ai-presentations#from_element=main_menu",
      "AI PDF to PPT Converter New Turn documents into PPT with AI": "https://slidesgo.com/ai-pdf-to-ppt-converter#from_element=main_menu",
      "AI Lesson Plan Generator Plan your lessons faster with AI": "https://slidesgo.com/ai-lesson-plan-generator#from_element=main_menu",
      "AI Icebreaker Generator Generate icebreaker activities and ideas": "https://slidesgo.com/ai-icebreaker-generator#from_element=main_menu",
      "AI Exit Ticket Generator Create quick formative assessments for your students": "https://slidesgo.com/ai-exit-ticket-generator#from_element=main_menu",
      "AI Quiz Maker beta Create comprehensive quizzes from any reading material": "https://slidesgo.com/ai/quiz-maker#from_element=main_menu",
      "Create Slideshows Create and customize presentations online with Slidesgo's editor": "https://slidesgo.com/slideshow-maker#from_element=main_menu",
      "Addon for Google Slides Apply Slidesgo themes to your Google Slides presentations": "https://workspace.google.com/marketplace/app/slidesgo_for_google_slides/560773215564#from_element=main_menu",
      "Explore all AI tools": "https://slidesgo.com/ai",
      "Infographics Templates for turning data and information into visual presentations": "https://slidesgo.com/infographics#from_element=main_menu",
      "Disney New content Templates with your favorite Disney and Pixar characters": "https://slidesgo.com/disney#from_element=main_menu",
      "Slidesclass Monthly drops Ready-to-use slides for any subject to simplify your lesson planning": "https://slidesgo.com/slidesclass#from_element=main_menu",
      "Business": "https://slidesgo.com/business#from_element=main_menu",
      "Technology": "https://slidesgo.com/technology#from_element=main_menu",
      "Law": "https://slidesgo.com/law#from_element=main_menu",
      "Sport": "https://slidesgo.com/sport#from_element=main_menu",
      "Architecture": "https://slidesgo.com/architecture#from_element=main_menu",
      "Fashion": "https://slidesgo.com/fashion#from_element=main_menu",
      "Money": "https://slidesgo.com/money#from_element=main_menu",
      "Medical": "https://slidesgo.com/medical#from_element=main_menu",
      "Health": "https://slidesgo.com/health#from_element=main_menu",
      "Mental Health": "https://slidesgo.com/mental-health#from_element=main_menu",
      "Disease": "https://slidesgo.com/disease#from_element=main_menu",
      "Case Report": "https://slidesgo.com/case-report#from_element=main_menu",
      "Marketing": "https://slidesgo.com/marketing#from_element=main_menu",
      "Newsletter": "https://slidesgo.com/newsletter#from_element=main_menu",
      "Campaign": "https://slidesgo.com/campaign#from_element=main_menu",
      "Instagram": "https://slidesgo.com/instagram#from_element=main_menu",
      "Social Media": "https://slidesgo.com/social-media#from_element=main_menu",
      "Popular": "https://slidesgo.com/themes#from_element=main_menu",
      "Food": "https://slidesgo.com/food#from_element=main_menu",
      "Nature": "https://slidesgo.com/nature#from_element=main_menu",
      "Travel": "https://slidesgo.com/travel#from_element=main_menu",
      "Water": "https://slidesgo.com/water#from_element=main_menu",
      "Space": "https://slidesgo.com/space#from_element=main_menu",
      "Minimalist": "https://slidesgo.com/minimalist#from_element=main_menu",
      "Aesthetic": "https://slidesgo.com/aesthetic#from_element=main_menu",
      "Simple": "https://slidesgo.com/simple#from_element=main_menu",
      "Cute": "https://slidesgo.com/cute#from_element=main_menu",
      "Professional": "https://slidesgo.com/professional#from_element=main_menu",
      "Vintage": "https://slidesgo.com/vintage#from_element=main_menu",
      "Black": "https://slidesgo.com/black#from_element=main_menu",
      "White": "https://slidesgo.com/white#from_element=main_menu",
      "Gray": "https://slidesgo.com/gray#from_element=main_menu",
      "Silver": "https://slidesgo.com/silver#from_element=main_menu",
      "Purple": "https://slidesgo.com/purple#from_element=main_menu",
      "Blue": "https://slidesgo.com/blue#from_element=main_menu",
      "Green": "https://slidesgo.com/green#from_element=main_menu",
      "Yellow": "https://slidesgo.com/yellow#from_element=main_menu",
      "Orange": "https://slidesgo.com/orange#from_element=main_menu",
      "Brown": "https://slidesgo.com/brown#from_element=main_menu",
      "Gold": "https://slidesgo.com/gold#from_element=main_menu",
      "Cream": "https://slidesgo.com/cream#from_element=main_menu",
      "Red": "https://slidesgo.com/red#from_element=main_menu",
      "Pink": "https://slidesgo.com/pink#from_element=main_menu",
      "Explore recent templates": "https://slidesgo.com/recent",
      "Coloring Page": "https://slidesgo.com/coloring-page#from_element=main_menu",
      "Workshop": "https://slidesgo.com/workshop#from_element=main_menu",
      "About Me": "https://slidesgo.com/about-me#from_element=main_menu",
      "Back to School": "https://slidesgo.com/back-to-school#from_element=main_menu",
      "Lesson": "https://slidesgo.com/lesson#from_element=main_menu",
      "Thesis Defense": "https://slidesgo.com/thesis-defense#from_element=main_menu",
      "Printable": "https://slidesgo.com/printable#from_element=main_menu",
      "History": "https://slidesgo.com/history#from_element=main_menu",
      "Science": "https://slidesgo.com/science#from_element=main_menu",
      "Art": "https://slidesgo.com/art#from_element=main_menu",
      "Math": "https://slidesgo.com/math#from_element=main_menu",
      "Biology": "https://slidesgo.com/biology#from_element=main_menu",
      "Chemistry": "https://slidesgo.com/chemistry#from_element=main_menu",
      "Geography": "https://slidesgo.com/geography#from_element=main_menu",
      "Psychology": "https://slidesgo.com/psychology#from_element=main_menu",
      "Literature": "https://slidesgo.com/literature#from_element=main_menu",
      "Pre-K": "https://slidesgo.com/pre-k#from_element=main_menu",
      "Elementary": "https://slidesgo.com/elementary#from_element=main_menu",
      "Middle School": "https://slidesgo.com/middle-school#from_element=main_menu",
      "High School": "https://slidesgo.com/high-school#from_element=main_menu",
      "University": "https://slidesgo.com/university#from_element=main_menu",
      "AI tools for education Start creating with AI, for teachers and students": "https://slidesgo.com/ai#from_element=main_menu",
      "Smartick Discover the world of mathematics like never before with Smartick!": "https://slidesgo.com/smartick#from_element=main_menu",
      "Teacher Toolkit Ready-to-edit educational materials": "https://slidesgo.com/teacher-toolkit#from_element=main_menu",
      "Explore all education templates": "https://slidesgo.com/education",
      "Blog Articles and other resources": "https://slidesgo.com/slidesgo-school",
      "PowerPoint Tutorials Learn how to work with Microsoft PowerPoint": "https://slidesgo.com/slidesgo-school/powerpoint-tutorials",
      "Google Slides Tutorials Discover the secrets of Google Slides": "https://slidesgo.com/slidesgo-school/google-slides-tutorials",
      "Presentation Tips The best tips on how to make an excellent presentation": "https://slidesgo.com/slidesgo-school/presentation-tips",
      "Slidesgo Teacher Community Join a global community of teachers and educators sharing tips and tools": "https://www.facebook.com/groups/1129415331402945",
      "Freepik Free vectors, photos and PSD": "https://www.freepik.com/",
      "Flaticon Free customizable icons": "https://www.flaticon.com/",
      "Storyset Free editable illustrations": "https://storyset.com/",
      "Videvo Free videos and motion graphics": "https://www.videvo.net/",
      "Plans & Pricing": "https://slidesgo.com/pricing",
      "Slidesgo for Schools and Districts Save money when your school buys together": "https://slidesgo.com/for-education-contact-us",
      "See now": "https://slidesgo.com/search?q=Moana%202",
      "Disney 363 templates": "https://slidesgo.com/disney",
      "Editor’s Choice 3082 templates": "https://slidesgo.com/editors-choice",
      "Printable Slides 1001 templates": "https://slidesgo.com/printable-slides",
      "Infographics 2795 templates": "https://slidesgo.com/infographics",
      "Slidesclass 667 templates": "https://slidesgo.com/slidesclass",
      "Minimalist 4159 templates": "https://slidesgo.com/minimalist",
      "Spring 261 templates": "https://slidesgo.com/spring",
      "Winter 208 templates": "https://slidesgo.com/winter",
      "Black History Month 39 templates": "https://slidesgo.com/black-history-month",
      "African American 75 templates": "https://slidesgo.com/african-american",
      "Kindergarten Sight Word Sentences & Games": "https://slidesgo.com/theme/kindergarten-sight-word-sentences-games#position-1&rs=home-latest&rs=home-latest",
      "Go Premium": "https://slidesgo.com/pricing?slide=happy-fall-theme-minimalist&utm_source=Premium&utm_medium=template&utm_campaign=premium-slides-microfunnel&utm_term=Go-Premium&utm_content=Happy+Fall+Theme",
      "Steps Infographics": "https://slidesgo.com/theme/steps-infographics-simple#position-2&rs=home-latest&rs=home-latest",
      "Team Org Charts Infographics": "https://slidesgo.com/theme/team-org-charts-infographics#position-3&rs=home-latest&rs=home-latest",
      "World History Key Moments for High School": "https://slidesgo.com/theme/world-history-key-moments-for-high-school#position-4&rs=home-latest&rs=home-latest",
      "Wind Instrument Makers Shop": "https://slidesgo.com/theme/wind-instrument-makers-shop#position-5&rs=home-latest&rs=home-latest",
      "Nature Style Aesthetic": "https://slidesgo.com/theme/nature-style-aesthetic#position-6&rs=home-latest&rs=home-latest",
      "Multi-purpose": "https://slidesgo.com/multi-purpose#rs=footer",
      "Irish Inspired Lucky Clover Stickers Personal Organizers for Students": "https://slidesgo.com/theme/irish-inspired-lucky-clover-stickers-personal-organizers-for-students-cute#position-1&rs=home-popular&rs=home-popular",
      "Minimalist Business Slides": "https://slidesgo.com/theme/minimalist-business-slides#position-2&rs=home-popular&rs=home-popular",
      "Go Premium to customize online": "https://slidesgo.com/pricing?slide=colorful-theme&utm_source=Premium&utm_medium=template&utm_campaign=premium-slides-microfunnel&utm_term=Go-Premium&utm_content=Colorful+Theme",
      "Colorful Theme": "https://slidesgo.com/theme/colorful-theme#position-3&rs=home-popular&rs=home-popular",
      "Spring Woods": "https://slidesgo.com/theme/spring-woods-cute#position-4&rs=home-popular&rs=home-popular",
      "Spring Party": "https://slidesgo.com/theme/spring-party#position-5&rs=home-popular&rs=home-popular",
      "Minimalist Korean Aesthetic Pitch Deck": "https://slidesgo.com/theme/minimalist-korean-aesthetic-pitch-deck#position-6&rs=home-popular&rs=home-popular",
      "Map of South Korea Infographics": "https://slidesgo.com/theme/map-of-south-korea-infographics#position-1&rs=home-infographics&rs=home-infographics",
      "Sales Funnel Infographics": "https://slidesgo.com/theme/sales-funnel-infographics#position-2&rs=home-infographics&rs=home-infographics",
      "Travel Infographics": "https://slidesgo.com/theme/travel-infographics-aesthetic#position-3&rs=home-infographics&rs=home-infographics",
      "Science 1133 templates": "https://slidesgo.com/science",
      "Art 872 templates": "https://slidesgo.com/art#rs=home",
      "Math 637 templates": "https://slidesgo.com/math",
      "Workshop 955 templates": "https://slidesgo.com/workshop",
      "Literacy 136 templates": "https://slidesgo.com/literacy",
      "Lesson 830 templates": "https://slidesgo.com/lesson",
      "School 4300 templates": "https://slidesgo.com/school",
      "Thesis Defense 1021 templates": "https://slidesgo.com/thesis-defense",
      "Music 431 templates": "https://slidesgo.com/music#rs=home",
      "Teacher Toolkit 122 templates": "https://slidesgo.com/teacher-toolkit",
      "Ocean Deeps Research Poster": "https://slidesgo.com/theme/ocean-deeps-research-poster#position-1&rs=home-interactive-animated&rs=home-interactive-animated",
      "What is AI Technology?": "https://slidesgo.com/theme/what-is-ai-technology#position-2&rs=home-interactive-animated&rs=home-interactive-animated",
      "Happy Fall Theme": "https://slidesgo.com/theme/happy-fall-theme-minimalist#position-3&rs=home-interactive-animated&rs=home-interactive-animated",
      "See editable in Canva themes": "https://slidesgo.com/editable-in-canva",
      "Make presentations with AI More info": "https://slidesgo.com/ai-presentations#rs=whatsnew",
      "Top 8 About me presentation templates for going back to school More info": "https://slidesgo.com/slidesgo-school/inspiration-by-slidesgo/top-8-about-me-presentation-templates-for-going-back-to-school#rs=whatsnew",
      "Make school fun from day one with Disney and Pixar templates More info": "https://slidesgo.com/slidesgo-school/inspiration-by-slidesgo/make-school-fun-from-day-one-with-disney-and-pixar-templates#rs=whatsnew",
      "Sales 176 templates": "https://slidesgo.com/sales#rs=home",
      "Travel 449 templates": "https://slidesgo.com/travel#rs=home",
      "Animal 1248 templates": "https://slidesgo.com/animal#rs=home",
      "Health 3853 templates": "https://slidesgo.com/health#rs=home",
      "History 1476 templates": "https://slidesgo.com/history#rs=home",
      "Environment 552 templates": "https://slidesgo.com/environment#rs=home",
      "Galaxy 198 templates": "https://slidesgo.com/galaxy#rs=home",
      "Fashion 249 templates": "https://slidesgo.com/fashion#rs=home",
      "Biology 564 templates": "https://slidesgo.com/biology#rs=home",
      "Summer 257 templates": "https://slidesgo.com/summer#rs=home",
      "Architecture 158 templates": "https://slidesgo.com/architecture#rs=home",
      "Research 1679 templates": "https://slidesgo.com/research#rs=home",
      "Culture 2140 templates": "https://slidesgo.com/culture#rs=home",
      "Background 10381 templates": "https://slidesgo.com/background#rs=home",
      "Back to School 214 templates": "https://slidesgo.com/back-to-school#rs=home",
      "Coloring Page 353 templates": "https://slidesgo.com/coloring-page#rs=home",
      "Black Friday 19 templates": "https://slidesgo.com/black-friday#rs=home",
      "Cyber Monday 9 templates": "https://slidesgo.com/cyber-monday#rs=home",
      "Become ambassador": "https://slidesgo.com/ambassadors",
      "Suggestion box": "https://forms.gle/mUYJ5G2oCnGoCAQE8",
      "Slidesclass": "https://slidesgo.com/slidesclass#rs=footer",
      "Printable Slides": "https://slidesgo.com/printable-slides#rs=footer",
      "Resources Pack": "https://slidesgo.com/resources-pack#rs=footer",
      "News": "https://slidesgo.com/slidesgo-school/news",
      "Inspiration by Slidesgo": "https://slidesgo.com/slidesgo-school/inspiration-by-slidesgo",
      "FAQs": "https://slidesgo.com/faqs",
      "Contact": "https://slidesgo.com/profile/support",
      "Terms & conditions": "https://slidesgo.com/terms-conditions",
      "Privacy policy": "https://www.freepik.com/legal/privacy",
      "Cookies policy": "https://slidesgo.com/legal/cookies",
      "About us": "https://www.freepik.com/company/about-us",
      "Español": "https://slidesgo.com/es/",
      "Português": "https://slidesgo.com/pt/",
      "Français": "https://slidesgo.com/fr/",
      "Deutsch": "https://slidesgo.com/de/",
      "한국어": "https://slidesgo.com/ko/"
    },
    "title": "Free Google Slides themes and Powerpoint templates",
    "description": "Discover the best Google Slides themes and PowerPoint templates you can use in your presentations - 100% Free for any use.",
    "url": "https://slidesgo.com/",
    "content": "Free Google Slides themes and Powerpoint templates | Slidesgo\n===============\n\n[![Image 1: Slidesgo](https://slidesgo.com/images/logos/slidesgo.svg)](https://slidesgo.com/)\n\nAI Tools New\n\nAI Tools\n\n[AI Presentation Maker Create presentations in minutes with AI](https://slidesgo.com/ai-presentations#from_element=main_menu)[AI PDF to PPT Converter New Turn documents into PPT with AI](https://slidesgo.com/ai-pdf-to-ppt-converter#from_element=main_menu)[AI Lesson Plan Generator Plan your lessons faster with AI](https://slidesgo.com/ai-lesson-plan-generator#from_element=main_menu)[AI Icebreaker Generator Generate icebreaker activities and ideas](https://slidesgo.com/ai-icebreaker-generator#from_element=main_menu)[AI Exit Ticket Generator Create quick formative assessments for your students](https://slidesgo.com/ai-exit-ticket-generator#from_element=main_menu)[AI Quiz Maker beta Create comprehensive quizzes from any reading material](https://slidesgo.com/ai/quiz-maker#from_element=main_menu)\n\nOther tools\n\n[Create Slideshows Create and customize presentations online with Slidesgo's editor](https://slidesgo.com/slideshow-maker#from_element=main_menu)[Addon for Google Slides Apply Slidesgo themes to your Google Slides presentations](https://workspace.google.com/marketplace/app/slidesgo_for_google_slides/560773215564#from_element=main_menu)\n\n[Explore all AI tools](https://slidesgo.com/ai)\n\nTemplates\n\nCollections\n\n[Infographics Templates for turning data and information into visual presentations](https://slidesgo.com/infographics#from_element=main_menu) [Disney New content Templates with your favorite Disney and Pixar characters](https://slidesgo.com/disney#from_element=main_menu) [Slidesclass Monthly drops Ready-to-use slides for any subject to simplify your lesson planning](https://slidesgo.com/slidesclass#from_element=main_menu)\n\nBy industry\n\n[Business](https://slidesgo.com/business)\n\n[Technology](https://slidesgo.com/technology#from_element=main_menu) [Law](https://slidesgo.com/law#from_element=main_menu) [Sport](https://slidesgo.com/sport#from_element=main_menu) [Architecture](https://slidesgo.com/architecture#from_element=main_menu) [Fashion](https://slidesgo.com/fashion#from_element=main_menu) [Money](https://slidesgo.com/money#from_element=main_menu)\n\n[Medical](https://slidesgo.com/medical)\n\n[Health](https://slidesgo.com/health#from_element=main_menu) [Mental Health](https://slidesgo.com/mental-health#from_element=main_menu) [Disease](https://slidesgo.com/disease#from_element=main_menu) [Case Report](https://slidesgo.com/case-report#from_element=main_menu)\n\n[Marketing](https://slidesgo.com/marketing)\n\n[Newsletter](https://slidesgo.com/newsletter#from_element=main_menu) [Campaign](https://slidesgo.com/campaign#from_element=main_menu) [Instagram](https://slidesgo.com/instagram#from_element=main_menu) [Social Media](https://slidesgo.com/social-media#from_element=main_menu)\n\n[Popular](https://slidesgo.com/themes)\n\n[Food](https://slidesgo.com/food#from_element=main_menu) [Nature](https://slidesgo.com/nature#from_element=main_menu) [Travel](https://slidesgo.com/travel#from_element=main_menu) [Water](https://slidesgo.com/water#from_element=main_menu) [Space](https://slidesgo.com/space#from_element=main_menu)\n\nBy style\n\n[Minimalist](https://slidesgo.com/minimalist#from_element=main_menu) [Aesthetic](https://slidesgo.com/aesthetic#from_element=main_menu) [Simple](https://slidesgo.com/simple#from_element=main_menu) [Cute](https://slidesgo.com/cute#from_element=main_menu) [Professional](https://slidesgo.com/professional#from_element=main_menu) [Vintage](https://slidesgo.com/vintage#from_element=main_menu)\n\nBy color\n\n[Black](https://slidesgo.com/black#from_element=main_menu) [White](https://slidesgo.com/white#from_element=main_menu) [Gray](https://slidesgo.com/gray#from_element=main_menu) [Silver](https://slidesgo.com/silver#from_element=main_menu) [Purple](https://slidesgo.com/purple#from_element=main_menu) [Blue](https://slidesgo.com/blue#from_element=main_menu) [Green](https://slidesgo.com/green#from_element=main_menu) [Yellow](https://slidesgo.com/yellow#from_element=main_menu) [Orange](https://slidesgo.com/orange#from_element=main_menu) [Brown](https://slidesgo.com/brown#from_element=main_menu) [Gold](https://slidesgo.com/gold#from_element=main_menu) [Cream](https://slidesgo.com/cream#from_element=main_menu) [Red](https://slidesgo.com/red#from_element=main_menu) [Pink](https://slidesgo.com/pink#from_element=main_menu)\n\n[Explore recent templates](https://slidesgo.com/recent)\n\nEducation Hub\n\nBy content type\n\n[Coloring Page](https://slidesgo.com/coloring-page#from_element=main_menu) [Workshop](https://slidesgo.com/workshop#from_element=main_menu) [About Me](https://slidesgo.com/about-me#from_element=main_menu) [Back to School](https://slidesgo.com/back-to-school#from_element=main_menu) [Lesson](https://slidesgo.com/lesson#from_element=main_menu) [Thesis Defense](https://slidesgo.com/thesis-defense#from_element=main_menu) [Printable](https://slidesgo.com/printable#from_element=main_menu)\n\nBy subject\n\n[History](https://slidesgo.com/history#from_element=main_menu) [Science](https://slidesgo.com/science#from_element=main_menu) [Art](https://slidesgo.com/art#from_element=main_menu) [Math](https://slidesgo.com/math#from_element=main_menu) [Biology](https://slidesgo.com/biology#from_element=main_menu) [Chemistry](https://slidesgo.com/chemistry#from_element=main_menu) [Geography](https://slidesgo.com/geography#from_element=main_menu) [Psychology](https://slidesgo.com/psychology#from_element=main_menu) [Literature](https://slidesgo.com/literature#from_element=main_menu)\n\nBy school level\n\n[Pre-K](https://slidesgo.com/pre-k#from_element=main_menu) [Elementary](https://slidesgo.com/elementary#from_element=main_menu) [Middle School](https://slidesgo.com/middle-school#from_element=main_menu) [High School](https://slidesgo.com/high-school#from_element=main_menu) [University](https://slidesgo.com/university#from_element=main_menu)\n\nFeatured resources\n\n[AI tools for education Start creating with AI, for teachers and students](https://slidesgo.com/ai#from_element=main_menu) [Slidesclass Ready-to-use slides for any subject to simplify your lesson planning](https://slidesgo.com/slidesclass#from_element=main_menu) [Smartick Discover the world of mathematics like never before with Smartick!](https://slidesgo.com/smartick#from_element=main_menu) [Teacher Toolkit Ready-to-edit educational materials](https://slidesgo.com/teacher-toolkit#from_element=main_menu)\n\n[Explore all education templates](https://slidesgo.com/education)\n\nLearn\n\n[Blog Articles and other resources](https://slidesgo.com/slidesgo-school) [PowerPoint Tutorials Learn how to work with Microsoft PowerPoint](https://slidesgo.com/slidesgo-school/powerpoint-tutorials) [Google Slides Tutorials Discover the secrets of Google Slides](https://slidesgo.com/slidesgo-school/google-slides-tutorials) [Presentation Tips The best tips on how to make an excellent presentation](https://slidesgo.com/slidesgo-school/presentation-tips) [Slidesgo Teacher Community Join a global community of teachers and educators sharing tips and tools](https://www.facebook.com/groups/1129415331402945)\n\nPDF\n\n### Templates\n\n  ![Image 2](https://slidesgo.com/images/icons/premium.svg) ![Image 3](https://slidesgo.com/images/icons/premium-xl.svg)![Image 4: related](https://slidesgo.com/)\n\n###  \n\nTop searches\n\n[aesthetic](https://slidesgo.com/search?q=aesthetic#rs=topsearches) [simple](https://slidesgo.com/search?q=simple#rs=topsearches) [history](https://slidesgo.com/search?q=history#rs=topsearches) [school](https://slidesgo.com/search?q=school#rs=topsearches) [minimalist](https://slidesgo.com/search?q=minimalist#rs=topsearches) [business](https://slidesgo.com/search?q=business#rs=topsearches) [technology](https://slidesgo.com/search?q=technology#rs=topsearches) [science](https://slidesgo.com/search?q=science#rs=topsearches) [music](https://slidesgo.com/search?q=music#rs=topsearches)\n\nTrending searches\n\n[![Image 5](https://media.slidesgo.com/storage/48970625/its-spring-break1708006865.jpg) ![Image 6](https://media.slidesgo.com/storage/48970625/its-spring-break1708006865.jpg) ![Image 7](https://media.slidesgo.com/storage/48970625/its-spring-break1708006865.jpg) #### spring break 19 templates](https://slidesgo.com/search?q=spring+break#rs=collections-trending-searches)[![Image 8](https://media.slidesgo.com/storage/31026087/lets-celebrate-st-patricks-day1675860180.jpg) ![Image 9](https://media.slidesgo.com/storage/31026087/lets-celebrate-st-patricks-day1675860180.jpg) ![Image 10](https://media.slidesgo.com/storage/31026087/lets-celebrate-st-patricks-day1675860180.jpg) #### st patricks day 13 templates](https://slidesgo.com/search?q=st+patricks+day#rs=collections-trending-searches)[![Image 11](https://media.slidesgo.com/storage/33888291/korean-food-workshop1681365748.jpg) ![Image 12](https://media.slidesgo.com/storage/33888291/korean-food-workshop1681365748.jpg) ![Image 13](https://media.slidesgo.com/storage/33888291/korean-food-workshop1681365748.jpg) #### korean food 8 templates](https://slidesgo.com/search?q=korean+food#rs=collections-trending-searches)[![Image 14](https://media.slidesgo.com/storage/23060309/irish-inspired-lucky-clover-stickers-personal-organizers-for-students1658325539.jpg) ![Image 15](https://media.slidesgo.com/storage/23060309/irish-inspired-lucky-clover-stickers-personal-organizers-for-students1658325539.jpg) ![Image 16](https://media.slidesgo.com/storage/23060309/irish-inspired-lucky-clover-stickers-personal-organizers-for-students1658325539.jpg) #### leprechaun 13 templates](https://slidesgo.com/search?q=leprechaun#rs=collections-trending-searches)[![Image 17](https://media.slidesgo.com/storage/22116090/1920s-fashion-thesis-statement1654757624.jpg) ![Image 18](https://media.slidesgo.com/storage/22116090/1920s-fashion-thesis-statement1654757624.jpg) ![Image 19](https://media.slidesgo.com/storage/22116090/1920s-fashion-thesis-statement1654757624.jpg) #### 1920s 16 templates](https://slidesgo.com/search?q=1920s#rs=collections-trending-searches)[![Image 20](https://media.slidesgo.com/storage/50606934/holy-week1710754487.jpg) ![Image 21](https://media.slidesgo.com/storage/50606934/holy-week1710754487.jpg) ![Image 22](https://media.slidesgo.com/storage/50606934/holy-week1710754487.jpg) #### holy week 24 templates](https://slidesgo.com/search?q=holy+week#rs=collections-trending-searches)\n\nMore\n\n[Freepik Free vectors, photos and PSD](https://www.freepik.com/) [Flaticon Free customizable icons](https://www.flaticon.com/) [Storyset Free editable illustrations](https://storyset.com/) [Videvo Free videos and motion graphics](https://www.videvo.net/)\n\n[Plans & Pricing](https://slidesgo.com/pricing)\n\n[Pricing Discover benefits of Premium plan](https://slidesgo.com/pricing)[Slidesgo for Schools and Districts Save money when your school buys together](https://slidesgo.com/for-education)\n\n    Log in\n\nCreate engaging presentations, faster\n=====================================\n\nFree templates for Google Slides, PowerPoint and Canva\n------------------------------------------------------\n\nPDF\n\n### Templates\n\n  ![Image 23](https://slidesgo.com/images/icons/premium.svg) ![Image 24](https://slidesgo.com/images/icons/premium-xl.svg)![Image 25: related](https://slidesgo.com/)\n\n###  \n\nTop searches\n\n[aesthetic](https://slidesgo.com/search?q=aesthetic#rs=topsearches) [simple](https://slidesgo.com/search?q=simple#rs=topsearches) [history](https://slidesgo.com/search?q=history#rs=topsearches) [school](https://slidesgo.com/search?q=school#rs=topsearches) [minimalist](https://slidesgo.com/search?q=minimalist#rs=topsearches) [business](https://slidesgo.com/search?q=business#rs=topsearches) [technology](https://slidesgo.com/search?q=technology#rs=topsearches)\n\nTrending searches\n\n[![Image 26](https://media.slidesgo.com/storage/48970625/its-spring-break1708006865.jpg) ![Image 27](https://media.slidesgo.com/storage/48970625/its-spring-break1708006865.jpg) ![Image 28](https://media.slidesgo.com/storage/48970625/its-spring-break1708006865.jpg) #### spring break 19 templates](https://slidesgo.com/search?q=spring+break#rs=collections-trending-searches)[![Image 29](https://media.slidesgo.com/storage/31026087/lets-celebrate-st-patricks-day1675860180.jpg) ![Image 30](https://media.slidesgo.com/storage/31026087/lets-celebrate-st-patricks-day1675860180.jpg) ![Image 31](https://media.slidesgo.com/storage/31026087/lets-celebrate-st-patricks-day1675860180.jpg) #### st patricks day 13 templates](https://slidesgo.com/search?q=st+patricks+day#rs=collections-trending-searches)[![Image 32](https://media.slidesgo.com/storage/33888291/korean-food-workshop1681365748.jpg) ![Image 33](https://media.slidesgo.com/storage/33888291/korean-food-workshop1681365748.jpg) ![Image 34](https://media.slidesgo.com/storage/33888291/korean-food-workshop1681365748.jpg) #### korean food 8 templates](https://slidesgo.com/search?q=korean+food#rs=collections-trending-searches)[![Image 35](https://media.slidesgo.com/storage/23060309/irish-inspired-lucky-clover-stickers-personal-organizers-for-students1658325539.jpg) ![Image 36](https://media.slidesgo.com/storage/23060309/irish-inspired-lucky-clover-stickers-personal-organizers-for-students1658325539.jpg) ![Image 37](https://media.slidesgo.com/storage/23060309/irish-inspired-lucky-clover-stickers-personal-organizers-for-students1658325539.jpg) #### leprechaun 13 templates](https://slidesgo.com/search?q=leprechaun#rs=collections-trending-searches)\n\n### Or kick off your next project with\n\nAI Presentation Maker\n\nExplore Disney’s latest! New Moana 2 content available\n\n[See now](https://slidesgo.com/search?q=Moana%202)\n\n### Trending searches\n\n[![Image 38: Disney](https://media.slidesgo.com/storage/69406640/conversions/stitch-angel1738164580-thumb.jpg) ![Image 39](https://media.slidesgo.com/storage/69406640/conversions/stitch-angel1738164580-thumb.jpg) ![Image 40](https://media.slidesgo.com/storage/69406640/conversions/stitch-angel1738164580-thumb.jpg) ### Disney 363 templates](https://slidesgo.com/disney)\n\n[![Image 41: Editor’s Choice](https://media.slidesgo.com/storage/71243985/conversions/inspirational-professional-style-template1740127459-thumb.jpg) ![Image 42](https://media.slidesgo.com/storage/71243985/conversions/inspirational-professional-style-template1740127459-thumb.jpg) ![Image 43](https://media.slidesgo.com/storage/71243985/conversions/inspirational-professional-style-template1740127459-thumb.jpg) ### Editor’s Choice 3082 templates](https://slidesgo.com/editors-choice)\n\n[![Image 44: Printable Slides](https://media.slidesgo.com/storage/73014667/conversions/Untitled-presentation-(5)-thumb.jpg) ![Image 45](https://media.slidesgo.com/storage/73014667/conversions/Untitled-presentation-(5)-thumb.jpg) ![Image 46](https://media.slidesgo.com/storage/73014667/conversions/Untitled-presentation-(5)-thumb.jpg) ### Printable Slides 1001 templates](https://slidesgo.com/printable-slides)\n\n[![Image 47: Infographics](https://media.slidesgo.com/storage/69516092/conversions/project-management-schedule-infographics1738321665-thumb.jpg) ![Image 48](https://media.slidesgo.com/storage/69516092/conversions/project-management-schedule-infographics1738321665-thumb.jpg) ![Image 49](https://media.slidesgo.com/storage/69516092/conversions/project-management-schedule-infographics1738321665-thumb.jpg) ### Infographics 2795 templates](https://slidesgo.com/infographics)\n\n[![Image 50: Slidesclass](https://media.slidesgo.com/storage/69517977/conversions/learning-situation-5-language-and-literature-2nd-grade1738324715-thumb.jpg) ![Image 51](https://media.slidesgo.com/storage/69517977/conversions/learning-situation-5-language-and-literature-2nd-grade1738324715-thumb.jpg) ![Image 52](https://media.slidesgo.com/storage/69517977/conversions/learning-situation-5-language-and-literature-2nd-grade1738324715-thumb.jpg) ### Slidesclass 667 templates](https://slidesgo.com/slidesclass)\n\n[![Image 53: Minimalist](https://media.slidesgo.com/storage/53808587/conversions/corporate-interior-design-workshop1715769047-thumb.jpg) ![Image 54](https://media.slidesgo.com/storage/53808587/conversions/corporate-interior-design-workshop1715769047-thumb.jpg) ![Image 55](https://media.slidesgo.com/storage/53808587/conversions/corporate-interior-design-workshop1715769047-thumb.jpg) ### Minimalist 4159 templates](https://slidesgo.com/minimalist)\n\n[![Image 56: Spring](https://media.slidesgo.com/storage/70399687/conversions/spring-season-aesthetic1739440176-thumb.jpg) ![Image 57](https://media.slidesgo.com/storage/70399687/conversions/spring-season-aesthetic1739440176-thumb.jpg) ![Image 58](https://media.slidesgo.com/storage/70399687/conversions/spring-season-aesthetic1739440176-thumb.jpg) ### Spring 261 templates](https://slidesgo.com/spring)\n\n[![Image 59: Winter](https://media.slidesgo.com/storage/55430095/conversions/finland-minitheme1718105222-thumb.jpg) ![Image 60](https://media.slidesgo.com/storage/55430095/conversions/finland-minitheme1718105222-thumb.jpg) ![Image 61](https://media.slidesgo.com/storage/55430095/conversions/finland-minitheme1718105222-thumb.jpg) ### Winter 208 templates](https://slidesgo.com/winter)\n\n[![Image 62: Black History Month](https://media.slidesgo.com/storage/68561762/conversions/black-history-month-reflection-honoring-frederick-douglass1736777752-thumb.jpg) ![Image 63](https://media.slidesgo.com/storage/68561762/conversions/black-history-month-reflection-honoring-frederick-douglass1736777752-thumb.jpg) ![Image 64](https://media.slidesgo.com/storage/68561762/conversions/black-history-month-reflection-honoring-frederick-douglass1736777752-thumb.jpg) ### Black History Month 39 templates](https://slidesgo.com/black-history-month)\n\n[![Image 65: African American](https://media.slidesgo.com/storage/68662661/conversions/african-american-heritage-month1736933255-thumb.jpg) ![Image 66](https://media.slidesgo.com/storage/68662661/conversions/african-american-heritage-month1736933255-thumb.jpg) ![Image 67](https://media.slidesgo.com/storage/68662661/conversions/african-american-heritage-month1736933255-thumb.jpg) ### African American 75 templates](https://slidesgo.com/african-american)\n\n### Latest themes\n\n[![Image 68: Kindergarten Sight Word Sentences & Games presentation template ](https://media.slidesgo.com/storage/11123326/0-kindergarten-sight-word-sentences-games.jpg) ![Image 69: Kindergarten Sight Word Sentences & Games presentation template ](https://slidesgo.com/) ![Image 70: Kindergarten Sight Word Sentences & Games presentation template ](https://media.slidesgo.com/storage/11123328/conversions/1-kindergarten-sight-word-sentences-games-thumb.jpg)](https://slidesgo.com/theme/kindergarten-sight-word-sentences-games#position-1&rs=home-latest)\n\n/\n\nLike\n\n ![Image 71](https://slidesgo.com/images/illustrations/brush-purple.svg) ![Image 72](https://slidesgo.com/images/icons/heart-icon.svg)\n\n### It seems that you like this template!\n\nBy registering on Slidesgo, you will be able to save templates as favorites so you can easily find them later. If you are already registered, log in!\n\n    Log in\n\nDownload\n\nDownload and open in Google Slides\n\nDownload as a PowerPoint file\n\nDownload and open in Canva\n\n![Image 73](https://slidesgo.com/images/illustrations/premium-creativity.png)\n\n### Register for free and start downloading now\n\nRegister on our website to download 3 FREE templates every month, or GO Premium for unlimited downloads!\n\n    Log in [Go Premium](https://slidesgo.com/pricing)\n\n### [Kindergarten Sight Word Sentences & Games](https://slidesgo.com/theme/kindergarten-sight-word-sentences-games#position-1&rs=home-latest&rs=home-latest)\n\nWhen learning the English language, there are some words that are very common, but also difficult to spell because they do not follow the normal rules of spelling. Of course, this is relevant at very young ages, so we have decided to create a new template for teachers, and it...\n\nA4\n\n[![Image 74: Steps Infographics presentation template ](https://media.slidesgo.com/storage/70176772/steps-infographics1739264205.jpg) ![Image 75: Steps Infographics presentation template ](https://slidesgo.com/) ![Image 76: Steps Infographics presentation template ](https://media.slidesgo.com/storage/70176719/conversions/1-steps-infographics-thumb.jpg)](https://slidesgo.com/theme/steps-infographics-simple#position-2&rs=home-latest)\n\n/\n\nLike\n\nDownload\n\n### ![Image 77: Premium subscription](https://slidesgo.com/images/icons/premium.svg) Premium template\n\nUnlock this template and gain unlimited access\n\n[Go Premium](https://slidesgo.com/pricing?slide=steps-infographics-simple&utm_source=Premium&utm_medium=template&utm_campaign=premium-slides-microfunnel&utm_term=Go-Premium&utm_content=Steps+Infographics)Are you already Premium? [Log in](javascript:document.querySelector('#login').submit())\n\n### [Steps Infographics](https://slidesgo.com/theme/steps-infographics-simple#position-2&rs=home-latest&rs=home-latest)\n\nDownload the Steps Infographics template for PowerPoint or Google Slides and discover the power of infographics. An infographic resource gives you the ability to showcase your content in a more visual way, which will make it easier for your audience to understand your topic. Slidesgo infographics like this set here...\n\n16:9\n\n[![Image 78: Team Org Charts Infographics presentation template ](https://media.slidesgo.com/storage/71974731/team-org-charts-infographics1740666334.jpg) ![Image 79: Team Org Charts Infographics presentation template ](https://slidesgo.com/) ![Image 80: Team Org Charts Infographics presentation template ](https://media.slidesgo.com/storage/71974583/conversions/1-team-org-charts-infographics-thumb.jpg)](https://slidesgo.com/theme/team-org-charts-infographics#position-3&rs=home-latest)\n\n/\n\nLike\n\nDownload\n\n### ![Image 81: Premium subscription](https://slidesgo.com/images/icons/premium.svg) Premium template\n\nUnlock this template and gain unlimited access\n\n[Go Premium](https://slidesgo.com/pricing?slide=team-org-charts-infographics&utm_source=Premium&utm_medium=template&utm_campaign=premium-slides-microfunnel&utm_term=Go-Premium&utm_content=Team+Org+Charts+Infographics)Are you already Premium? [Log in](javascript:document.querySelector('#login').submit())\n\n### [Team Org Charts Infographics](https://slidesgo.com/theme/team-org-charts-infographics#position-3&rs=home-latest&rs=home-latest)\n\nDownload the Team Org Charts Infographics template for PowerPoint or Google Slides to get the most out of infographics. Whether you want to organize your business budget in a table or schematically analyze your sales over the past year, this set of infographic resources will be of great help. Start...\n\n16:9\n\n[![Image 82: World History Key Moments for High School presentation template ](https://media.slidesgo.com/storage/72677912/world-history-key-moments-for-high-school1741168262.jpg) ![Image 83: World History Key Moments for High School presentation template ](https://slidesgo.com/) ![Image 84: World History Key Moments for High School presentation template ](https://media.slidesgo.com/storage/72677516/conversions/1-world-history-key-moments-for-high-school-thumb.jpg)](https://slidesgo.com/theme/world-history-key-moments-for-high-school#position-4&rs=home-latest)\n\n/\n\nLike\n\nDownload\n\n### ![Image 85: Premium subscription](https://slidesgo.com/images/icons/premium.svg) Premium template\n\nUnlock this template and gain unlimited access\n\n[Go Premium](https://slidesgo.com/pricing?slide=world-history-key-moments-for-high-school&utm_source=Premium&utm_medium=template&utm_campaign=premium-slides-microfunnel&utm_term=Go-Premium&utm_content=World+History+Key+Moments+for+High+School)Are you already Premium? [Log in](javascript:document.querySelector('#login').submit())\n\n### [World History Key Moments for High School](https://slidesgo.com/theme/world-history-key-moments-for-high-school#position-4&rs=home-latest&rs=home-latest)\n\nDownload the World History Key Moments for High School presentation for PowerPoint or Google Slides. High school students are approaching adulthood, and therefore, this template’s design reflects the mature nature of their education. Customize the well-defined sections, integrate multimedia and interactive elements and allow space for research or group projects...\n\n16:9\n\n[![Image 86: Wind Instrument Makers Shop presentation template ](https://media.slidesgo.com/storage/49488634/wind-instrument-makers-shop1708948527.jpg) ![Image 87: Wind Instrument Makers Shop presentation template ](https://slidesgo.com/) ![Image 88: Wind Instrument Makers Shop presentation template ](https://media.slidesgo.com/storage/49488226/conversions/1-wind-instrument-makers-shop-thumb.jpg)](https://slidesgo.com/theme/wind-instrument-makers-shop#position-5&rs=home-latest)\n\n/\n\nLike\n\nDownload\n\nCustomize online Customize online Generate content with AI\n\nDownload and open in Google Slides\n\nDownload as a PowerPoint file\n\nDownload and open in Canva\n\n### [Wind Instrument Makers Shop](https://slidesgo.com/theme/wind-instrument-makers-shop#position-5&rs=home-latest&rs=home-latest)\n\nDownload the \"Wind Instrument Makers Shop\" presentation for PowerPoint or Google Slides. Presenting a comprehensive company profile can be a game-changer for your business. A well-crafted profile connects with potential clients and vendors on another level, giving them a deep understanding of your organization. This company profile template can help...\n\n16:9\n\n[![Image 89: Nature Style Aesthetic presentation template ](https://media.slidesgo.com/storage/71697446/nature-style-aesthetic1740481865.jpg) ![Image 90: Nature Style Aesthetic presentation template ](https://slidesgo.com/) ![Image 91: Nature Style Aesthetic presentation template ](https://media.slidesgo.com/storage/71697192/conversions/1-nature-style-aesthetic-thumb.jpg)](https://slidesgo.com/theme/nature-style-aesthetic#position-6&rs=home-latest)\n\n/\n\nLike\n\nDownload\n\n### ![Image 92: Premium subscription](https://slidesgo.com/images/icons/premium.svg) Premium template\n\nUnlock this template and gain unlimited access\n\n[Go Premium](https://slidesgo.com/pricing?slide=nature-style-aesthetic&utm_source=Premium&utm_medium=template&utm_campaign=premium-slides-microfunnel&utm_term=Go-Premium&utm_content=Nature+Style+Aesthetic)Are you already Premium? [Log in](javascript:document.querySelector('#login').submit())\n\n### [Nature Style Aesthetic](https://slidesgo.com/theme/nature-style-aesthetic#position-6&rs=home-latest&rs=home-latest)\n\nDownload the Nature Style Aesthetic presentation for PowerPoint or Google Slides and start impressing your audience with a creative and original design. Slidesgo templates like this one here offer the possibility to convey a concept, idea or topic in a clear, concise and visual way, by using different graphic resources....\n\n[Multi-purpose](https://slidesgo.com/multi-purpose)\n\n16:9\n\n[Latest themes](https://slidesgo.com/recent)\n\n### Popular themes\n\n[![Image 93: Irish Inspired Lucky Clover Stickers Personal Organizers for Students presentation template ](https://media.slidesgo.com/storage/48970478/irish-inspired-lucky-clover-stickers-personal-organizers-for-students1708006789.jpg) ![Image 94: Irish Inspired Lucky Clover Stickers Personal Organizers for Students presentation template ](https://slidesgo.com/) ![Image 95: Irish Inspired Lucky Clover Stickers Personal Organizers for Students presentation template ](https://media.slidesgo.com/storage/48970014/conversions/1-irish-inspired-lucky-clover-stickers-personal-organizers-for-students-thumb.jpg)](https://slidesgo.com/theme/irish-inspired-lucky-clover-stickers-personal-organizers-for-students-cute#position-1&rs=home-popular)\n\n/\n\nLike\n\nDownload\n\n### ![Image 96: Premium subscription](https://slidesgo.com/images/icons/premium.svg) Premium template\n\nUnlock this template and gain unlimited access\n\n[Go Premium](https://slidesgo.com/pricing?slide=irish-inspired-lucky-clover-stickers-personal-organizers-for-students-cute&utm_source=Premium&utm_medium=template&utm_campaign=premium-slides-microfunnel&utm_term=Go-Premium&utm_content=Irish+Inspired+Lucky+Clover+Stickers+Personal+Organizers+for+Students)Are you already Premium? [Log in](javascript:document.querySelector('#login').submit())\n\n### [Irish Inspired Lucky Clover Stickers Personal Organizers for Students](https://slidesgo.com/theme/irish-inspired-lucky-clover-stickers-personal-organizers-for-students-cute#position-1&rs=home-popular&rs=home-popular)\n\nDownload the \"Irish Inspired Lucky Clover Stickers Personal Organizers for Students\" presentation for PowerPoint or Google Slides. The education sector constantly demands dynamic and effective ways to present information. This template is created with that very purpose in mind. Offering the best resources, it allows educators or students to efficiently...\n\n[Multi-purpose](https://slidesgo.com/multi-purpose)\n\n16:9\n\n[![Image 97: Minimalist Business Slides presentation template ](https://media.slidesgo.com/storage/39117931/minimalist-business-slides1691669242.jpg) ![Image 98: Minimalist Business Slides presentation template ](https://slidesgo.com/) ![Image 99: Minimalist Business Slides presentation template ](https://media.slidesgo.com/storage/39117292/conversions/1-minimalist-business-slides-thumb.jpg)](https://slidesgo.com/theme/minimalist-business-slides#position-2&rs=home-popular)\n\n/\n\nLike\n\nDownload\n\nCustomize online Customize online Generate content with AI Generate content with AI\n\nDownload and open in Google Slides\n\nDownload as a PowerPoint file\n\nDownload and open in Canva\n\n### [Minimalist Business Slides](https://slidesgo.com/theme/minimalist-business-slides#position-2&rs=home-popular&rs=home-popular)\n\nMinimalism is an art style that frees the canvas and that lets the content stand out for itself. It’s a way of conveying modernism, simplicity and elegance and can be your best ally in your next presentation. With this new design from Slidesgo, your business presentations will be as professional...\n\nPost 16:9\n\n[![Image 100: Colorful Theme presentation template ](https://media.slidesgo.com/storage/53881255/colorful-theme1715844376.jpg) ![Image 101: Colorful Theme presentation template ](https://slidesgo.com/) ![Image 102: Colorful Theme presentation template ](https://media.slidesgo.com/storage/53880949/conversions/1-colorful-theme-thumb.jpg)](https://slidesgo.com/theme/colorful-theme#position-3&rs=home-popular)\n\n/\n\nLike\n\nDownload\n\n[Go Premium to customize online](https://slidesgo.com/pricing?slide=colorful-theme&utm_source=Premium&utm_medium=template&utm_campaign=premium-slides-microfunnel&utm_term=Go-Premium&utm_content=Colorful+Theme) [Go Premium to customize online](https://slidesgo.com/pricing?slide=colorful-theme&utm_source=Premium&utm_medium=template&utm_campaign=premium-slides-microfunnel&utm_term=Go-Premium&utm_content=Colorful+Theme) Generate content with AI\n\n### ![Image 103: Premium subscription](https://slidesgo.com/images/icons/premium.svg) Premium template\n\nUnlock this template and gain unlimited access\n\n[Go Premium](https://slidesgo.com/pricing?slide=colorful-theme&utm_source=Premium&utm_medium=template&utm_campaign=premium-slides-microfunnel&utm_term=Go-Premium&utm_content=Colorful+Theme)Are you already Premium? [Log in](javascript:document.querySelector('#login').submit())\n\n### [Colorful Theme](https://slidesgo.com/theme/colorful-theme#position-3&rs=home-popular&rs=home-popular)\n\nDownload the Colorful Theme presentation for PowerPoint or Google Slides and start impressing your audience with a creative and original design. Slidesgo templates like this one here offer the possibility to convey a concept, idea or topic in a clear, concise and visual way, by using different graphic resources. You...\n\n[Multi-purpose](https://slidesgo.com/multi-purpose)\n\n16:9\n\n[![Image 104: Spring Woods presentation template ](https://media.slidesgo.com/storage/50000544/spring-woods1709722804.jpg) ![Image 105: Spring Woods presentation template ](https://slidesgo.com/) ![Image 106: Spring Woods presentation template ](https://media.slidesgo.com/storage/50000000/conversions/1-spring-woods-thumb.jpg)](https://slidesgo.com/theme/spring-woods-cute#position-4&rs=home-popular)\n\n/\n\nLike\n\nDownload\n\n### ![Image 107: Premium subscription](https://slidesgo.com/images/icons/premium.svg) Premium template\n\nUnlock this template and gain unlimited access\n\n[Go Premium](https://slidesgo.com/pricing?slide=spring-woods-cute&utm_source=Premium&utm_medium=template&utm_campaign=premium-slides-microfunnel&utm_term=Go-Premium&utm_content=Spring+Woods)Are you already Premium? [Log in](javascript:document.querySelector('#login').submit())\n\n### [Spring Woods](https://slidesgo.com/theme/spring-woods-cute#position-4&rs=home-popular&rs=home-popular)\n\nDownload the \"Spring Woods\" presentation for PowerPoint or Google Slides and start impressing your audience with a creative and original design. Slidesgo templates like this one here offer the possibility to convey a concept, idea or topic in a clear, concise and visual way, by using different graphic resources. You...\n\n[Multi-purpose](https://slidesgo.com/multi-purpose)\n\n16:9\n\n[![Image 108: Spring Party presentation template ](https://media.slidesgo.com/storage/49870162/spring-party1709547992.jpg) ![Image 109: Spring Party presentation template ](https://slidesgo.com/) ![Image 110: Spring Party presentation template ](https://media.slidesgo.com/storage/49869790/conversions/1-spring-party-thumb.jpg)](https://slidesgo.com/theme/spring-party#position-5&rs=home-popular)\n\n/\n\nLike\n\nDownload\n\n### ![Image 111: Premium subscription](https://slidesgo.com/images/icons/premium.svg) Premium template\n\nUnlock this template and gain unlimited access\n\n[Go Premium](https://slidesgo.com/pricing?slide=spring-party&utm_source=Premium&utm_medium=template&utm_campaign=premium-slides-microfunnel&utm_term=Go-Premium&utm_content=Spring+Party)Are you already Premium? [Log in](javascript:document.querySelector('#login').submit())\n\n### [Spring Party](https://slidesgo.com/theme/spring-party#position-5&rs=home-popular&rs=home-popular)\n\nDownload the \"Spring Party\" presentation for PowerPoint or Google Slides and start impressing your audience with a creative and original design. Slidesgo templates like this one here offer the possibility to convey a concept, idea or topic in a clear, concise and visual way, by using different graphic resources. You...\n\n[Multi-purpose](https://slidesgo.com/multi-purpose)\n\n16:9\n\n[![Image 112: Minimalist Korean Aesthetic Pitch Deck presentation template ](https://media.slidesgo.com/storage/71831013/minimalist-korean-aesthetic-pitch-deck1740572811.jpg) ![Image 113: Minimalist Korean Aesthetic Pitch Deck presentation template ](https://slidesgo.com/) ![Image 114: Minimalist Korean Aesthetic Pitch Deck presentation template ](https://media.slidesgo.com/storage/71830429/conversions/1-minimalist-korean-aesthetic-pitch-deck-thumb.jpg)](https://slidesgo.com/theme/minimalist-korean-aesthetic-pitch-deck#position-6&rs=home-popular)\n\n/\n\nLike\n\nDownload\n\nCustomize online Customize online Generate content with AI\n\nDownload and open in Google Slides\n\nDownload as a PowerPoint file\n\nDownload and open in Canva\n\n### [Minimalist Korean Aesthetic Pitch Deck](https://slidesgo.com/theme/minimalist-korean-aesthetic-pitch-deck#position-6&rs=home-popular&rs=home-popular)\n\nTemplates based on a minimalist style are usually very useful in business presentations, as they make the audience focus on the content and not on the ornaments of the design. This minimalist style template that we propose here is perfect for a pitch deck to present your product or your...\n\nPost 16:9\n\n[Popular themes](https://slidesgo.com/themes)\n\n#### Infographics\n\n[![Image 115: Map of South Korea Infographics presentation template ](https://media.slidesgo.com/storage/1142420/map-of-south-korea-infographics1607500384.png) ![Image 116: Map of South Korea Infographics presentation template ](https://slidesgo.com/) ![Image 117: Map of South Korea Infographics presentation template ](https://media.slidesgo.com/storage/1142344/conversions/1-map-of-south-korea-infographics-thumb.jpg)](https://slidesgo.com/theme/map-of-south-korea-infographics#position-1&rs=home-infographics)\n\n/\n\nLike\n\nDownload\n\nDownload and open in Google Slides\n\nDownload as a PowerPoint file\n\nDownload and open in Canva\n\n### [Map of South Korea Infographics](https://slidesgo.com/theme/map-of-south-korea-infographics#position-1&rs=home-infographics&rs=home-infographics)\n\nThe Asian continent has a lot of beautiful places to visit, and these infographics put South Korea in the spotlight. With lots of maps of this country and different infographic resources, it'll be easy for you to talk about the Korean regions, geography, demographics or just provide some statistics or...\n\n16:9\n\n[![Image 118: Sales Funnel Infographics presentation template ](https://media.slidesgo.com/storage/72828996/sales-funnel-infographics1741245770.jpg) ![Image 119: Sales Funnel Infographics presentation template ](https://slidesgo.com/) ![Image 120: Sales Funnel Infographics presentation template ](https://media.slidesgo.com/storage/72828893/conversions/1-sales-funnel-infographics-thumb.jpg)](https://slidesgo.com/theme/sales-funnel-infographics#position-2&rs=home-infographics)\n\n/\n\nLike\n\nDownload\n\n### ![Image 121: Premium subscription](https://slidesgo.com/images/icons/premium.svg) Premium template\n\nUnlock this template and gain unlimited access\n\n[Go Premium](https://slidesgo.com/pricing?slide=sales-funnel-infographics&utm_source=Premium&utm_medium=template&utm_campaign=premium-slides-microfunnel&utm_term=Go-Premium&utm_content=Sales+Funnel+Infographics)Are you already Premium? [Log in](javascript:document.querySelector('#login').submit())\n\n### [Sales Funnel Infographics](https://slidesgo.com/theme/sales-funnel-infographics#position-2&rs=home-infographics&rs=home-infographics)\n\nDownload the Sales Funnel Infographics template for PowerPoint or Google Slides to get the most out of infographics. Whether you want to organize your business budget in a table or schematically analyze your sales over the past year, this set of infographic resources will be of great help. Start using...\n\n16:9\n\n[![Image 122: Travel Infographics presentation template ](https://media.slidesgo.com/storage/72672629/travel-infographics1741165868.jpg) ![Image 123: Travel Infographics presentation template ](https://slidesgo.com/) ![Image 124: Travel Infographics presentation template ](https://media.slidesgo.com/storage/72672511/conversions/1-travel-infographics-thumb.jpg)](https://slidesgo.com/theme/travel-infographics-aesthetic#position-3&rs=home-infographics)\n\n/\n\nLike\n\nDownload\n\n### ![Image 125: Premium subscription](https://slidesgo.com/images/icons/premium.svg) Premium template\n\nUnlock this template and gain unlimited access\n\n[Go Premium](https://slidesgo.com/pricing?slide=travel-infographics-aesthetic&utm_source=Premium&utm_medium=template&utm_campaign=premium-slides-microfunnel&utm_term=Go-Premium&utm_content=Travel+Infographics)Are you already Premium? [Log in](javascript:document.querySelector('#login').submit())\n\n### [Travel Infographics](https://slidesgo.com/theme/travel-infographics-aesthetic#position-3&rs=home-infographics&rs=home-infographics)\n\nDownload the Travel Infographics template for PowerPoint or Google Slides and discover this set of editable infographics for education presentations. These resources, from graphs to tables, can be combined with other presentations or used independently. The most important thing is what you will achieve: transmit information in an orderly and...\n\n16:9\n\n[See infographics](https://slidesgo.com/infographics)\n\n### Education presentation templates\n\n[![Image 126: Slidesclass](https://media.slidesgo.com/storage/69517977/conversions/learning-situation-5-language-and-literature-2nd-grade1738324715-thumb.jpg) ![Image 127](https://media.slidesgo.com/storage/69517977/conversions/learning-situation-5-language-and-literature-2nd-grade1738324715-thumb.jpg) ![Image 128](https://media.slidesgo.com/storage/69517977/conversions/learning-situation-5-language-and-literature-2nd-grade1738324715-thumb.jpg) ### Slidesclass 667 templates](https://slidesgo.com/slidesclass)\n\n[![Image 129: Science](https://media.slidesgo.com/storage/63352994/conversions/what-are-the-properties-of-matter1729857036-thumb.jpg) ![Image 130](https://media.slidesgo.com/storage/63352994/conversions/what-are-the-properties-of-matter1729857036-thumb.jpg) ![Image 131](https://media.slidesgo.com/storage/63352994/conversions/what-are-the-properties-of-matter1729857036-thumb.jpg) ### Science 1133 templates](https://slidesgo.com/science)\n\n[![Image 132: Art](https://media.slidesgo.com/storage/71845451/conversions/learning-situation-9-language-and-literature-5th-grade1740580008-thumb.jpg) ![Image 133](https://media.slidesgo.com/storage/71845451/conversions/learning-situation-9-language-and-literature-5th-grade1740580008-thumb.jpg) ![Image 134](https://media.slidesgo.com/storage/71845451/conversions/learning-situation-9-language-and-literature-5th-grade1740580008-thumb.jpg) ### Art 872 templates](https://slidesgo.com/art)\n\n[![Image 135: Math](https://media.slidesgo.com/storage/70488954/conversions/math-subject-for-elementary-5th-grade-probability-infographics1739517667-thumb.jpg) ![Image 136](https://media.slidesgo.com/storage/70488954/conversions/math-subject-for-elementary-5th-grade-probability-infographics1739517667-thumb.jpg) ![Image 137](https://media.slidesgo.com/storage/70488954/conversions/math-subject-for-elementary-5th-grade-probability-infographics1739517667-thumb.jpg) ### Math 637 templates](https://slidesgo.com/math)\n\n[![Image 138: Workshop](https://media.slidesgo.com/storage/67806229/conversions/virtual-icebreaker1734689846-thumb.jpg) ![Image 139](https://media.slidesgo.com/storage/67806229/conversions/virtual-icebreaker1734689846-thumb.jpg) ![Image 140](https://media.slidesgo.com/storage/67806229/conversions/virtual-icebreaker1734689846-thumb.jpg) ### Workshop 955 templates](https://slidesgo.com/workshop)\n\n[![Image 141: Literacy](https://media.slidesgo.com/storage/67994743/conversions/learning-situation-1-language-and-literature-1st-grade1735299860-thumb.jpg) ![Image 142](https://media.slidesgo.com/storage/67994743/conversions/learning-situation-1-language-and-literature-1st-grade1735299860-thumb.jpg) ![Image 143](https://media.slidesgo.com/storage/67994743/conversions/learning-situation-1-language-and-literature-1st-grade1735299860-thumb.jpg) ### Literacy 136 templates](https://slidesgo.com/literacy)\n\n[![Image 144: Lesson](https://media.slidesgo.com/storage/69511343/conversions/science-lesson-plan1738313973-thumb.jpg) ![Image 145](https://media.slidesgo.com/storage/69511343/conversions/science-lesson-plan1738313973-thumb.jpg) ![Image 146](https://media.slidesgo.com/storage/69511343/conversions/science-lesson-plan1738313973-thumb.jpg) ### Lesson 830 templates](https://slidesgo.com/lesson)\n\n[![Image 147: School](https://media.slidesgo.com/storage/72890149/conversions/frog-life-cycle-playbook1741274920-thumb.jpg) ![Image 148](https://media.slidesgo.com/storage/72890149/conversions/frog-life-cycle-playbook1741274920-thumb.jpg) ![Image 149](https://media.slidesgo.com/storage/72890149/conversions/frog-life-cycle-playbook1741274920-thumb.jpg) ### School 4300 templates](https://slidesgo.com/school)\n\n[![Image 150: Thesis Defense](https://media.slidesgo.com/storage/72001635/conversions/street-maps-thesis1740678624-thumb.jpg) ![Image 151](https://media.slidesgo.com/storage/72001635/conversions/street-maps-thesis1740678624-thumb.jpg) ![Image 152](https://media.slidesgo.com/storage/72001635/conversions/street-maps-thesis1740678624-thumb.jpg) ### Thesis Defense 1021 templates](https://slidesgo.com/thesis-defense)\n\n[![Image 153: Music](https://media.slidesgo.com/storage/71250451/conversions/learning-situation-5-language-and-literature-5th-grade1740132157-thumb.jpg) ![Image 154](https://media.slidesgo.com/storage/71250451/conversions/learning-situation-5-language-and-literature-5th-grade1740132157-thumb.jpg) ![Image 155](https://media.slidesgo.com/storage/71250451/conversions/learning-situation-5-language-and-literature-5th-grade1740132157-thumb.jpg) ### Music 431 templates](https://slidesgo.com/music)\n\n[![Image 156: Teacher Toolkit](https://media.slidesgo.com/storage/38164886/conversions/kimok-science-doodles-style-lesson-template-daily-learning-stem1689246522-thumb.jpg) ![Image 157](https://media.slidesgo.com/storage/38164886/conversions/kimok-science-doodles-style-lesson-template-daily-learning-stem1689246522-thumb.jpg) ![Image 158](https://media.slidesgo.com/storage/38164886/conversions/kimok-science-doodles-style-lesson-template-daily-learning-stem1689246522-thumb.jpg) ### Teacher Toolkit 122 templates](https://slidesgo.com/teacher-toolkit)\n\n### Editable in Canva\n\n[![Image 159: Ocean Deeps Research Poster presentation template ](https://media.slidesgo.com/storage/22799145/0-ocean-deeps-research-poster.jpg) ![Image 160: Ocean Deeps Research Poster presentation template ](https://slidesgo.com/) ![Image 161: Ocean Deeps Research Poster presentation template ](https://media.slidesgo.com/storage/22799146/conversions/1-ocean-deeps-research-poster-thumb.jpg)](https://slidesgo.com/theme/ocean-deeps-research-poster#position-1&rs=home-interactive-animated)\n\n/\n\nLike\n\nDownload\n\nDownload and open in Google Slides\n\nDownload as a PowerPoint file\n\nDownload and open in Canva\n\n### [Ocean Deeps Research Poster](https://slidesgo.com/theme/ocean-deeps-research-poster#position-1&rs=home-interactive-animated&rs=home-interactive-animated)\n\nWe know more about space than we do about the deep ocean. What kinds of species hide down there? We dare you to google what kind of fish swim 10km below sea level, you’d be surprised… then, share your findings with this creative research poster and share everything you know...\n\n[Multi-purpose](https://slidesgo.com/multi-purpose)\n\n4:3\n\n[![Image 162: What is AI Technology? presentation template ](https://media.slidesgo.com/storage/73029014/what-is-ai-technology1741354089.jpg) ![Image 163: What is AI Technology? presentation template ](https://slidesgo.com/) ![Image 164: What is AI Technology? presentation template ](https://media.slidesgo.com/storage/73028567/conversions/1-what-is-ai-technology-thumb.jpg)](https://slidesgo.com/theme/what-is-ai-technology#position-2&rs=home-interactive-animated)\n\n/\n\nLike\n\nDownload\n\n### ![Image 165: Premium subscription](https://slidesgo.com/images/icons/premium.svg) Premium template\n\nUnlock this template and gain unlimited access\n\n[Go Premium](https://slidesgo.com/pricing?slide=what-is-ai-technology&utm_source=Premium&utm_medium=template&utm_campaign=premium-slides-microfunnel&utm_term=Go-Premium&utm_content=What+is+AI+Technology%3F)Are you already Premium? [Log in](javascript:document.querySelector('#login').submit())\n\n### [What is AI Technology?](https://slidesgo.com/theme/what-is-ai-technology#position-2&rs=home-interactive-animated&rs=home-interactive-animated)\n\nDownload the What is AI Technology? presentation for PowerPoint or Google Slides and start impressing your audience with a creative and original design. Slidesgo templates like this one here offer the possibility to convey a concept, idea or topic in a clear, concise and visual way, by using different graphic...\n\n[Multi-purpose](https://slidesgo.com/multi-purpose)\n\n16:9\n\n[![Image 166: Happy Fall Theme presentation template ](https://media.slidesgo.com/storage/73020337/happy-fall-theme1741349616.jpg) ![Image 167: Happy Fall Theme presentation template ](https://slidesgo.com/) ![Image 168: Happy Fall Theme presentation template ](https://media.slidesgo.com/storage/73020059/conversions/1-happy-fall-theme-thumb.jpg)](https://slidesgo.com/theme/happy-fall-theme-minimalist#position-3&rs=home-interactive-animated)\n\n/\n\nLike\n\nDownload\n\n### ![Image 169: Premium subscription](https://slidesgo.com/images/icons/premium.svg) Premium template\n\nUnlock this template and gain unlimited access\n\n[Go Premium](https://slidesgo.com/pricing?slide=happy-fall-theme-minimalist&utm_source=Premium&utm_medium=template&utm_campaign=premium-slides-microfunnel&utm_term=Go-Premium&utm_content=Happy+Fall+Theme)Are you already Premium? [Log in](javascript:document.querySelector('#login').submit())\n\n### [Happy Fall Theme](https://slidesgo.com/theme/happy-fall-theme-minimalist#position-3&rs=home-interactive-animated&rs=home-interactive-animated)\n\nDownload the Happy Fall Theme presentation for PowerPoint or Google Slides and start impressing your audience with a creative and original design. Slidesgo templates like this one here offer the possibility to convey a concept, idea or topic in a clear, concise and visual way, by using different graphic resources....\n\n[Multi-purpose](https://slidesgo.com/multi-purpose)\n\n16:9\n\n[See editable in Canva themes](https://slidesgo.com/editable-in-canva)\n\n#### What's new on Slidesgo\n\nSee the latest website updates, new features and tools and make the most of your Slidesgo experience.\n\n[![Image 170: AI presentation generator](https://slidesgo.com/images/ai/ai_preview.svg) ##### Make presentations with AI More info](https://slidesgo.com/ai-presentations#rs=whatsnew)[![Image 171: Top 8 About me presentation templates for going back to school | Quick Tips & Tutorial for your presentations](https://media.slidesgo.com/storage/59724130/upload.jpeg) ##### Top 8 About me presentation templates for going back to school More info](https://slidesgo.com/slidesgo-school/inspiration-by-slidesgo/top-8-about-me-presentation-templates-for-going-back-to-school#rs=whatsnew)[![Image 172: Make school fun from day one with Disney and Pixar templates | Quick Tips & Tutorial for your presentations](https://media.slidesgo.com/storage/59307391/upload.png) ##### Make school fun from day one with Disney and Pixar templates More info](https://slidesgo.com/slidesgo-school/inspiration-by-slidesgo/make-school-fun-from-day-one-with-disney-and-pixar-templates#rs=whatsnew)\n\n#### Browse by tags\n\n*   [Sales 176 templates](https://slidesgo.com/sales#rs=home)\n*   [Travel 449 templates](https://slidesgo.com/travel#rs=home)\n*   [Animal 1248 templates](https://slidesgo.com/animal#rs=home)\n*   [Art 872 templates](https://slidesgo.com/art#rs=home)\n*   [Health 3853 templates](https://slidesgo.com/health#rs=home)\n*   [History 1476 templates](https://slidesgo.com/history#rs=home)\n*   [Environment 552 templates](https://slidesgo.com/environment#rs=home)\n*   [Galaxy 198 templates](https://slidesgo.com/galaxy#rs=home)\n*   [Fashion 249 templates](https://slidesgo.com/fashion#rs=home)\n*   [Biology 564 templates](https://slidesgo.com/biology#rs=home)\n*   [Summer 257 templates](https://slidesgo.com/summer#rs=home)\n*   [Architecture 158 templates](https://slidesgo.com/architecture#rs=home)\n*   [Music 431 templates](https://slidesgo.com/music#rs=home)\n*   [Research 1679 templates](https://slidesgo.com/research#rs=home)\n*   [Culture 2140 templates](https://slidesgo.com/culture#rs=home)\n*   [Background 10381 templates](https://slidesgo.com/background#rs=home)\n*   [Back to School 214 templates](https://slidesgo.com/back-to-school#rs=home)\n*   [Coloring Page 353 templates](https://slidesgo.com/coloring-page#rs=home)\n*   [Black Friday 19 templates](https://slidesgo.com/black-friday#rs=home)\n*   [Cyber Monday 9 templates](https://slidesgo.com/cyber-monday#rs=home)\n\n### What do our users say about us?\n\n![Image 173: user testimonial avatar](https://slidesgo.com/images/testimonials/1.jpg)\n\nI just wanted to thank you! I learned more about slides in one day of quarantine than in my whole life\n\nGabriela Miranda\n\n![Image 174: user testimonial avatar](https://slidesgo.com/images/testimonials/2.jpg)\n\nYour slides are so unique and gorgeous! They really help me with PowerPoint presentations for school and now even my mom uses them for work\n\nMarie Dupuis\n\n![Image 175: user testimonial avatar](https://slidesgo.com/images/testimonials/3.jpg)\n\nI would like to thank to you for these amazing templates. I have never seen such service, especially free! They are very useful for my presentation.\n\nAli Serdar Çelikezen\n\n![Image 176: user testimonial avatar](https://slidesgo.com/images/testimonials/4.jpg)\n\nThank you Slidesgo for creating amazing templates for us. It's made my presentation become much better.\n\nThiên Trang Nguyễn\n\n![Image 177: Slidesgo logo](https://slidesgo.com/images/logos/slidesgo-by-freepik.svg)\n\nWork with us\n\n[Become ambassador](https://slidesgo.com/ambassadors)\n\n[Suggestion box](https://forms.gle/mUYJ5G2oCnGoCAQE8)\n\n### Social Media\n\n[](https://www.pinterest.es/slidesgo/)[](https://www.tiktok.com/@slidesgotemplates)[](https://twitter.com/slidesgo)[](https://www.instagram.com/slidesgo/)[](https://www.youtube.com/channel/UCwitIiMU0oUOHshx4pywqaw)\n\n### Content\n\n*   [Home](https://slidesgo.com/)\n*   [Recent](https://slidesgo.com/recent)\n*   [Popular](https://slidesgo.com/themes)\n*   [Slidesclass](https://slidesgo.com/slidesclass#rs=footer)\n*   [Multi-purpose](https://slidesgo.com/multi-purpose#rs=footer)\n*   [Printable Slides](https://slidesgo.com/printable-slides#rs=footer)\n*   [Resources Pack](https://slidesgo.com/resources-pack#rs=footer)\n\n### Learn\n\n*   [Blog](https://slidesgo.com/slidesgo-school)\n*   [News](https://slidesgo.com/slidesgo-school/news)\n*   [Inspiration by Slidesgo](https://slidesgo.com/slidesgo-school/inspiration-by-slidesgo)\n*   [Presentation Tips](https://slidesgo.com/slidesgo-school/presentation-tips)\n*   [Google Slides Tutorials](https://slidesgo.com/slidesgo-school/google-slides-tutorials)\n*   [PowerPoint Tutorials](https://slidesgo.com/slidesgo-school/powerpoint-tutorials)\n\n### Help\n\n*   *   [FAQs](https://slidesgo.com/faqs)\n    *   [Contact](https://slidesgo.com/profile/support)\n    *   Cookies Settings\n    *   [Terms & conditions](https://slidesgo.com/terms-conditions)\n    *   [Slidesgo Educator Community](https://www.facebook.com/groups/1129415331402945)\n*   *   [Privacy policy](https://www.freepik.com/legal/privacy)\n    *   [Cookies policy](https://slidesgo.com/legal/cookies)\n    *   [About us](https://www.freepik.com/company/about-us)\n\nCopyright ©2025 Freepik Company S.L. All rights reserved.\n\nEnglish\n\n[Español](https://slidesgo.com/es/) [English](https://slidesgo.com/) [Português](https://slidesgo.com/pt/) [Français](https://slidesgo.com/fr/) [Deutsch](https://slidesgo.com/de/) [한국어](https://slidesgo.com/ko/)\n\n**Freepik Company Projects**\n\n*   [Freepik](https://www.freepik.com/)\n*   [Flaticon](https://www.flaticon.com/)\n*   [Slidesgo](https://slidesgo.com/)\n*   [Videvo](https://www.videvo.net/)\n\nAI Tools New\n\nTemplates\n\nEducation Hub\n\nLearn\n\nPlans & Pricing\n\nMore\n\nAI Tools New\n\nAI Tools\n\n[AI Presentation Maker Create presentations in minutes with AI](https://slidesgo.com/ai-presentations#from_element=main_menu) [AI PDF to PPT Converter New Turn documents into PPT with AI](https://slidesgo.com/ai-pdf-to-ppt-converter#from_element=main_menu) [AI Lesson Plan Generator Plan your lessons faster with AI](https://slidesgo.com/ai-lesson-plan-generator#from_element=main_menu) [AI Icebreaker Generator Generate icebreaker activities and ideas](https://slidesgo.com/ai-icebreaker-generator#from_element=main_menu) [AI Exit Ticket Generator Create quick formative assessments for your students](https://slidesgo.com/ai-exit-ticket-generator#from_element=main_menu) [AI Quiz Maker beta Create comprehensive quizzes from any reading material](https://slidesgo.com/ai/quiz-maker#from_element=main_menu)\n\nOther tools\n\n[Create Slideshows Create and customize presentations online with Slidesgo's editor](https://slidesgo.com/slideshow-maker#from_element=main_menu) [Addon for Google Slides Apply Slidesgo themes to your Google Slides presentations](https://workspace.google.com/marketplace/app/slidesgo_for_google_slides/560773215564#from_element=main_menu)\n\n[Explore all AI tools](https://slidesgo.com/ai#from_element=main_menu)\n\nTemplates\n\nBy industry\n\nBusiness\n\nMedical\n\nMarketing\n\nPopular\n\nBy style\n\n[Minimalist](https://slidesgo.com/minimalist#from_element=main_menu) [Aesthetic](https://slidesgo.com/aesthetic#from_element=main_menu) [Simple](https://slidesgo.com/simple#from_element=main_menu) [Cute](https://slidesgo.com/cute#from_element=main_menu) [Professional](https://slidesgo.com/professional#from_element=main_menu) [Vintage](https://slidesgo.com/vintage#from_element=main_menu)\n\nBy color\n\n[Black](https://slidesgo.com/black#from_element=main_menu) [White](https://slidesgo.com/white#from_element=main_menu) [Gray](https://slidesgo.com/gray#from_element=main_menu) [Silver](https://slidesgo.com/silver#from_element=main_menu) [Purple](https://slidesgo.com/purple#from_element=main_menu) [Blue](https://slidesgo.com/blue#from_element=main_menu) [Green](https://slidesgo.com/green#from_element=main_menu) [Yellow](https://slidesgo.com/yellow#from_element=main_menu) [Orange](https://slidesgo.com/orange#from_element=main_menu) [Brown](https://slidesgo.com/brown#from_element=main_menu) [Gold](https://slidesgo.com/gold#from_element=main_menu) [Cream](https://slidesgo.com/cream#from_element=main_menu) [Red](https://slidesgo.com/red#from_element=main_menu) [Pink](https://slidesgo.com/pink#from_element=main_menu)\n\nCollections\n\n[Infographics Templates for turning data and information into visual presentations](https://slidesgo.com/infographics#from_element=main_menu) [Disney New content Templates with your favorite Disney and Pixar characters](https://slidesgo.com/disney#from_element=main_menu) [Slidesclass Ready-to-use slides for any subject to simplify your lesson planning](https://slidesgo.com/slidesclass#from_element=main_menu)\n\n[Explore recent templates](https://slidesgo.com/recent)\n\nTemplates\n\n[Business](https://slidesgo.com/business#from_element=main_menu) [Technology](https://slidesgo.com/technology#from_element=main_menu) [Law](https://slidesgo.com/law#from_element=main_menu) [Sport](https://slidesgo.com/sport#from_element=main_menu) [Architecture](https://slidesgo.com/architecture#from_element=main_menu) [Fashion](https://slidesgo.com/fashion#from_element=main_menu) [Money](https://slidesgo.com/money#from_element=main_menu) [Explore recent templates](https://slidesgo.com/recent)\n\nTemplates\n\n[Medical](https://slidesgo.com/medical#from_element=main_menu) [Health](https://slidesgo.com/health#from_element=main_menu) [Mental Health](https://slidesgo.com/mental-health#from_element=main_menu) [Disease](https://slidesgo.com/disease#from_element=main_menu) [Case Report](https://slidesgo.com/case-report#from_element=main_menu) [Explore recent templates](https://slidesgo.com/recent)\n\nTemplates\n\n[Marketing](https://slidesgo.com/marketing#from_element=main_menu) [Newsletter](https://slidesgo.com/newsletter#from_element=main_menu) [Campaign](https://slidesgo.com/campaign#from_element=main_menu) [Instagram](https://slidesgo.com/instagram#from_element=main_menu) [Social Media](https://slidesgo.com/social-media#from_element=main_menu) [Explore recent templates](https://slidesgo.com/recent)\n\nTemplates\n\n[Popular](https://slidesgo.com/themes#from_element=main_menu) [Food](https://slidesgo.com/food#from_element=main_menu) [Nature](https://slidesgo.com/nature#from_element=main_menu) [Travel](https://slidesgo.com/travel#from_element=main_menu) [Water](https://slidesgo.com/water#from_element=main_menu) [Space](https://slidesgo.com/space#from_element=main_menu) [Explore recent templates](https://slidesgo.com/recent)\n\nEducation Hub\n\nBy content type\n\n[Coloring Page](https://slidesgo.com/coloring-page#from_element=main_menu) [Workshop](https://slidesgo.com/workshop#from_element=main_menu) [About Me](https://slidesgo.com/about-me#from_element=main_menu) [Back to School](https://slidesgo.com/back-to-school#from_element=main_menu) [Lesson](https://slidesgo.com/lesson#from_element=main_menu) [Thesis Defense](https://slidesgo.com/thesis-defense#from_element=main_menu) [Printable](https://slidesgo.com/printable#from_element=main_menu)\n\nBy subject\n\n[History](https://slidesgo.com/history#from_element=main_menu) [Science](https://slidesgo.com/science#from_element=main_menu) [Art](https://slidesgo.com/art#from_element=main_menu) [Math](https://slidesgo.com/math#from_element=main_menu) [Biology](https://slidesgo.com/biology#from_element=main_menu) [Chemistry](https://slidesgo.com/chemistry#from_element=main_menu) [Geography](https://slidesgo.com/geography#from_element=main_menu) [Psychology](https://slidesgo.com/psychology#from_element=main_menu) [Literature](https://slidesgo.com/literature#from_element=main_menu)\n\nBy school level\n\n[Pre-K](https://slidesgo.com/pre-k#from_element=main_menu) [Elementary](https://slidesgo.com/elementary#from_element=main_menu) [Middle School](https://slidesgo.com/middle-school#from_element=main_menu) [High School](https://slidesgo.com/high-school#from_element=main_menu) [University](https://slidesgo.com/university#from_element=main_menu)\n\nFeatured resources\n\n[AI tools for education Start creating with AI, for teachers and students](https://slidesgo.com/ai#from_element=main_menu) [Slidesclass Ready-to-use slides for any subject to simplify your lesson planning](https://slidesgo.com/slidesclass#from_element=main_menu) [Smartick Discover the world of mathematics like never before with Smartick!](https://slidesgo.com/smartick#from_element=main_menu) [Teacher Toolkit Ready-to-edit educational materials](https://slidesgo.com/teacher-toolkit#from_element=main_menu)\n\n[Explore all education templates](https://slidesgo.com/education)\n\nLearn\n\n[Blog Articles and other resources](https://slidesgo.com/slidesgo-school) [PowerPoint Tutorials Learn how to work with Microsoft PowerPoint](https://slidesgo.com/slidesgo-school/powerpoint-tutorials) [Google Slides Tutorials Discover the secrets of Google Slides](https://slidesgo.com/slidesgo-school/google-slides-tutorials) [Presentation Tips The best tips on how to make an excellent presentation](https://slidesgo.com/slidesgo-school/presentation-tips) [Slidesgo Teacher Community Join a global community of teachers and educators sharing tips and tools](https://www.facebook.com/groups/1129415331402945)\n\nPlans & Pricing\n\n[Pricing Discover benefits of Premium plan](https://slidesgo.com/pricing) [Slidesgo for Schools and Districts Save money when your school buys together](https://slidesgo.com/for-education-contact-us)\n\nMore\n\n[Freepik Free vectors, photos and PSD](https://www.freepik.com/) [Flaticon Free customizable icons](https://www.flaticon.com/) [Storyset Free editable illustrations](https://storyset.com/) [Videvo Free videos and motion graphics](https://www.videvo.net/)\n\n         \n\n![Image 178](https://slidesgo.com/images/illustrations/premium-creativity.png)\n\n### Register for free and start editing online\n\nJust one quick step before editing: Sign up to Slidesgo. By registering in Slidesgo, you will be able to edit online templates and download up to 3 templates per month. If you are already registered, log in!\n\n    Register\n\n  \n\n![Image 179](https://slidesgo.com/images/illustrations/brush-purple.svg) ![Image 180](https://slidesgo.com/images/icons/heart-icon.svg)\n\n### It seems that you like this template!\n\nBy registering on Slidesgo, you will be able to save templates as favorites so you can easily find them later. If you are already registered, log in!\n\n    Log in\n\n![Image 181](https://slidesgo.com/images/illustrations/premium-creativity.png)\n\n### Register for free and start downloading now\n\nRegister on our website to download 3 FREE templates every month, or GO Premium for unlimited downloads!\n\n    Log in [Go Premium](https://slidesgo.com/pricing)\n\n![Image 182](https://slidesgo.com/images/illustrations/premium-creativity.png)\n\n### Register for free and start editing online\n\nJust one quick step before editing: Sign up to Slidesgo. By registering in Slidesgo, you will be able to edit online templates and download up to 3 templates per month. If you are already registered, log in!\n\n    Register\n\n### Create your presentation Create personalized presentation content\n\n![Image 183](https://slidesgo.com/)\n\n \n\n### Topic\n\n### Writing tone\n\n### Language\n\n### Number of slides\n\n### Style\n\n  Minimalist  Colorful  Geometric  Professional\n\n ![Image 184](https://slidesgo.com/)\n\n ![Image 185](https://slidesgo.com/)\n\n ![Image 186](https://slidesgo.com/images/landing/ai/minimalist.jpg)\n\n ![Image 187](https://slidesgo.com/images/landing/ai/cute.jpg)\n\n ![Image 188](https://slidesgo.com/images/landing/ai/duotone.jpg)\n\n ![Image 189](https://slidesgo.com/images/landing/ai/white.jpg)\n\n ![Image 190](https://slidesgo.com/images/landing/ai/simple.jpg)\n\n ![Image 191](https://slidesgo.com/images/landing/ai/company.jpg)\n\n ![Image 192](https://slidesgo.com/)\n\n ![Image 193](https://slidesgo.com/images/landing/ai/scrapbook.jpg)\n\n ![Image 194](https://slidesgo.com/images/landing/ai/cool.jpg)\n\n ![Image 195](https://slidesgo.com/images/landing/ai/futuristic.jpg)\n\n ![Image 196](https://slidesgo.com/images/landing/ai/gradient.jpg)\n\n ![Image 197](https://slidesgo.com/images/landing/ai/portfolio.jpg)\n\n ![Image 198](https://slidesgo.com/images/landing/ai/black.jpg)\n\n ![Image 199](https://slidesgo.com/)\n\n ![Image 200](https://slidesgo.com/images/landing/ai/report.jpg)\n\n ![Image 201](https://slidesgo.com/images/landing/ai/creative.jpg)\n\n ![Image 202](https://slidesgo.com/images/landing/ai/german.jpg)\n\n ![Image 203](https://slidesgo.com/images/landing/ai/math.jpg)\n\n ![Image 204](https://slidesgo.com/images/landing/ai/purple.jpg)\n\n ![Image 205](https://slidesgo.com/images/landing/ai/corporate.jpg)\n\n ![Image 206](https://slidesgo.com/)\n\n ![Image 207](https://slidesgo.com/images/landing/ai/professional.jpg)\n\n ![Image 208](https://slidesgo.com/images/landing/ai/elegant.jpg)\n\n ![Image 209](https://slidesgo.com/images/landing/ai/meeting.jpg)\n\n ![Image 210](https://slidesgo.com/images/landing/ai/research.jpg)\n\n ![Image 211](https://slidesgo.com/images/landing/ai/consulting.jpg)\n\n ![Image 212](https://slidesgo.com/images/landing/ai/picture.jpg)\n\nGenerate presentation Generate content\n\nBy clicking “Accept All Cookies”, you agree to the storing of cookies on your device to enhance site navigation, analyze site usage, and assist in our marketing efforts.\n\nCookies Settings Reject All Accept All Cookies\n\n![Image 213: Freepik](https://cdn-ukwest.onetrust.com/logos/efdbe2f5-d139-4c53-b573-973872d9f5e0/437406e3-68f5-4511-9b2a-ae1412064c97/e84522f2-4193-4c4b-969c-a8adce5a90d3/freepik-color.png)\n\nPrivacy Preference Center\n-------------------------\n\n*   ### Your Privacy\n    \n*   ### Strictly Necessary Cookies\n    \n*   ### Performance Cookies\n    \n*   ### Functional Cookies\n    \n*   ### Targeting Cookies\n    \n\n#### Your Privacy\n\nWhen you visit any website, it may store or retrieve information on your browser, mostly in the form of cookies. This information might be about you, your preferences or your device and is mostly used to make the site work as you expect it to. The information does not usually directly identify you, but it can give you a more personalized web experience. Because we respect your right to privacy, you can choose not to allow some types of cookies. Click on the different category headings to find out more and change our default settings. However, blocking some types of cookies may impact your experience of the site and the services we are able to offer.\n\nUser ID: 8318f86d-bfc3-4f69-9e7d-552a72b06d0f\n\nThis User ID will be used as a unique identifier while storing and accessing your preferences for future.\n\nTimestamp: \\--\n\n#### Strictly Necessary Cookies\n\nAlways Active\n\nThese cookies are necessary for the website to function and cannot be switched off in our systems. They are usually only set in response to actions made by you which amount to a request for services, such as setting your privacy preferences, logging in or filling in forms. You can set your browser to block or alert you about these cookies, but some parts of the site will not then work. These cookies do not store any personally identifiable information.\n\n#### Performance Cookies\n\n Performance Cookies\n\nThese cookies allow us to count visits and traffic sources so we can measure and improve the performance of our site. They help us to know which pages are the most and least popular and see how visitors move around the site. All information these cookies collect is aggregated and therefore anonymous. If you do not allow these cookies we will not know when you have visited our site, and will not be able to monitor its performance.\n\n#### Functional Cookies\n\n Functional Cookies\n\nThese cookies enable the website to provide enhanced functionality and personalisation. They may be set by us or by third party providers whose services we have added to our pages. If you do not allow these cookies then some or all of these services may not function properly.\n\n#### Targeting Cookies\n\n Targeting Cookies\n\nThese cookies may be set through our site by our advertising partners. They may be used by those companies to build a profile of your interests and show you relevant adverts on other sites. They do not store directly personal information, but are based on uniquely identifying your browser and internet device. If you do not allow these cookies, you will experience less targeted advertising.\n\n### Cookie List\n\nConsent Leg.Interest\n\n checkbox label label\n\n checkbox label label\n\n checkbox label label\n\nClear\n\n checkbox label label\n\nApply Cancel\n\nConfirm My Choices\n\nReject All Allow All\n\n[![Image 214: Powered by Onetrust](https://cdn-ukwest.onetrust.com/logos/static/powered_by_logo.svg)](https://www.onetrust.com/products/cookie-consent/)",
    "usage": {
      "tokens": 17330
    }
  }
}